cqbear/__init__.py
cqbear/bear.py
cqbear/remember.py
cqbear/roar.py
cqbear/sentence.py
cqbear/sound.py
cqbear/util.py
cqbear-0.4.dist-info/LICENSE
cqbear-0.4.dist-info/METADATA
cqbear-0.4.dist-info/WHEEL
cqbear-0.4.dist-info/top_level.txt
cqbear-0.4.dist-info/RECORD
