Metadata-Version: 2.1
Name: cqbear
Version: 0.4
Summary: A bear-like bot python module for go-cqhttp.
Home-page: https://github.com/ChenSmallX/CqBear
Author: ChenSmallX
Author-email: 641751205@qq.com
License: GNU
Keywords: go-cqhttp,qqbot,Mirai,MiraiGo
Platform: UNKNOWN
Classifier: Intended Audience :: Developers
Classifier: License :: OSI Approved :: GNU General Public License (GPL)
Classifier: Operating System :: OS Independent
Classifier: Natural Language :: Chinese (Simplified)
Classifier: Programming Language :: Python :: 3
Requires-Python: >=3.4.0
License-File: LICENSE
Requires-Dist: Flask (==2.0.1)
Requires-Dist: requests (==2.22.0)
Requires-Dist: setuptools (==45.2.0)
